ebook2text/VERSION.py
ebook2text/__init__.py
ebook2text/_exceptions.py
ebook2text/_logger.py
ebook2text/_types.py
ebook2text/chapter_check.py
ebook2text/convert_file.py
ebook2text/ocr.py
ebook2text/text_parser.py
ebook2text/text_utilities.py
ebook2text/docx_conversion/__init__.py
ebook2text/docx_conversion/_namespaces.py
ebook2text/docx_conversion/docx_converter.py
ebook2text/docx_conversion/docx_image_extractor.py
ebook2text/docx_conversion/docx_text_extractor.py
ebook2text/epub_conversion/__init__.py
ebook2text/epub_conversion/epub_converter.py
ebook2text/epub_conversion/epub_text_extractor.py
ebook2text/pdf_conversion/__init__.py
ebook2text/pdf_conversion/_enums.py
ebook2text/pdf_conversion/pdf_converter.py
ebook2text/pdf_conversion/pdf_image_extractor.py
ebook2text/pdf_conversion/pdf_line_logic.py
ebook2text/pdf_conversion/pdf_text_extractor.py
ebook2text-2.2.0.dist-info/METADATA
ebook2text-2.2.0.dist-info/WHEEL
ebook2text-2.2.0.dist-info/top_level.txt
ebook2text-2.2.0.dist-info/RECORD
