Metadata-Version: 2.4
Name: ebook2text
Version: 2.2.0
Summary: Convert common book file types to text for machine learning
Author: Ashlynn Antrobus
Author-email: Ashlynn Antrobus <ashlynn@prosepal.io>
License: MIT
Project-URL: Repository, https://github.com/ashrobertsdragon/Ebook-conversion-to-Text-for-Machine-Learning
Classifier: License :: OSI Approved :: MIT License
Classifier: Development Status :: 5 - Production/Stable
Classifier: Intended Audience :: Developers
Classifier: Environment :: Console
Classifier: Operating System :: OS Independent
Classifier: Programming Language :: Python
Classifier: Programming Language :: Python :: 3
Classifier: Programming Language :: Python :: 3 :: Only
Classifier: Programming Language :: Python :: 3.9
Classifier: Programming Language :: Python :: 3.10
Classifier: Programming Language :: Python :: 3.11
Classifier: Programming Language :: Python :: 3.12
Classifier: Programming Language :: Python :: 3.13
Classifier: Topic :: Scientific/Engineering :: Artificial Intelligence
Classifier: Topic :: Text Processing
Requires-Python: >=3.10
Requires-Dist: beautifulsoup4>=4.12.3
Requires-Dist: ebooklib-autoupdate>=0.18.3
Requires-Dist: openai>=1.54.3
Requires-Dist: pdfminer-six>=20240706
Requires-Dist: pillow>=10.4.0
Requires-Dist: python-docx>=1.1.2
Requires-Dist: python-dotenv>=1.0.1
Dynamic: author
